setup.py
bin/dxpy
dxl_dxpy.egg-info/PKG-INFO
dxl_dxpy.egg-info/SOURCES.txt
dxl_dxpy.egg-info/dependency_links.txt
dxl_dxpy.egg-info/not-zip-safe
dxl_dxpy.egg-info/requires.txt
dxl_dxpy.egg-info/top_level.txt
dxpy/__init__.py
dxpy/config.old.py
dxpy/config.py
dxpy/core.py
dxpy/database.py
dxpy/time.py
dxpy/utils.py
dxpy/api/__init__.py
dxpy/api/cli.py
dxpy/api/config.py
dxpy/batch/__init__.py
dxpy/batch/config.py
dxpy/batch/exceptions.py
dxpy/batch/service.py
dxpy/batch/api/__init__.py
dxpy/batch/api/api.py
dxpy/batch/api/web.py
dxpy/batch/api/cli/__init__.py
dxpy/batch/api/cli/commands.py
dxpy/batch/api/cli/main.py
dxpy/batch/model/__init__.py
dxpy/batch/model/filters.py
dxpy/batch/model/operators.py
dxpy/code/__init__.py
dxpy/code/scripts.py
dxpy/code/service.py
dxpy/code/snippet.py
dxpy/code/api/__init__.py
dxpy/code/api/api.py
dxpy/code/api/cli.py
dxpy/code/asserts/__init__.py
dxpy/code/asserts/_convertable.py
dxpy/code/debug/__init__.py
dxpy/code/debug/temp_run.py
dxpy/code/exceptions/__init__.py
dxpy/code/exceptions/_exceptions.py
dxpy/code/exceptions/message.py
dxpy/collections/__init__.py
dxpy/collections/trees.py
dxpy/collections/dicts/__init__.py
dxpy/collections/dicts/_core.py
dxpy/collections/dicts/_exceptions.py
dxpy/collections/dicts/utils.py
dxpy/configs/__init__.py
dxpy/configs/_configurable.py
dxpy/configs/_setter.py
dxpy/configs/_viewer.py
dxpy/configs/module_config.py
dxpy/configs/configs_new/__init__.py
dxpy/configs/configs_new/_combine.py
dxpy/configs/configs_new/_configable.py
dxpy/configs/configs_new/_configs.py
dxpy/core/__init__.py
dxpy/core/code/__init__.py
dxpy/core/code/_exceptions.py
dxpy/core/code/_messages.py
dxpy/core/path/__init__.py
dxpy/core/path/_exceptions.py
dxpy/core/path/_path.py
dxpy/core/path/_serilization.py
dxpy/core/path/_urlpath.py
dxpy/debug/__init__.py
dxpy/debug/config.py
dxpy/debug/utils.py
dxpy/exceptions/__init__.py
dxpy/exceptions/checks.py
dxpy/exceptions/http.py
dxpy/file_system/__init__.py
dxpy/file_system/file.py
dxpy/file_system/file_system.py
dxpy/file_system/path.py
dxpy/filesystem/__init__.py
dxpy/filesystem/exceptions.py
dxpy/filesystem/service.py
dxpy/filesystem/smartfs.py
