Metadata-Version: 1.0
Name: dxl-dxpy
Version: 0.7.62
Summary: Duplicate components library python library.
Home-page: https://github.com/Hong-Xiang/dxl
Author: Hong Xiang
Author-email: hx.hongxiang@gmail.com
License: MIT
Platform: UNKNOWN
